{
  "id": "5bb44094f3a4530013560bac",
  "title": "マッチョとウィンプ",
  "created": 1538539694,
  "updated": 1538548818,
  "lines": [
    {
      "id": "5bb44094f3a4530013560bac",
      "text": "マッチョとウィンプ",
      "userId": "582e63d27c56960011aff09e",
      "created": 1538539694,
      "updated": 1538539696
    },
    {
      "id": "5bb46332aff09e000019d81b",
      "text": "明確なコンセンサスのない人間の性格の二分法",
      "userId": "582e63d27c56960011aff09e",
      "created": 1538548531,
      "updated": 1538548566
    },
    {
      "id": "5bb46356aff09e000019d81d",
      "text": "キャッチーなので2008年ぐらいに日本のインターネットの一部で盛り上がった",
      "userId": "582e63d27c56960011aff09e",
      "created": 1538548566,
      "updated": 1538548566
    },
    {
      "id": "5bb46340aff09e000019d81c",
      "text": "",
      "userId": "582e63d27c56960011aff09e",
      "created": 1538548544,
      "updated": 1538548544
    },
    {
      "id": "5bb440b0aff09e00008de958",
      "text": "https://www.google.co.jp/search?q=マッチョとウィンプ&aqs=chrome.1.69i57j0.6157j0j7&sourceid=chrome&ie=UTF-8",
      "userId": "582e63d27c56960011aff09e",
      "created": 1538539696,
      "updated": 1538539705
    },
    {
      "id": "5bb46247aff09e000019d811",
      "text": "",
      "userId": "582e63d27c56960011aff09e",
      "created": 1538548295,
      "updated": 1538548295
    },
    {
      "id": "5bb440b0aff09e00008de959",
      "text": "2008",
      "userId": "582e63d27c56960011aff09e",
      "created": 1538539697,
      "updated": 1538548386
    },
    {
      "id": "5bb46435aff09e000019d823",
      "text": "\t2008-03-02",
      "userId": "582e63d27c56960011aff09e",
      "created": 1538548789,
      "updated": 1538548791
    },
    {
      "id": "5bb46437aff09e000019d824",
      "text": " \t[2010年、マッチョ主義によって日本社会のとてつもない大改革が始まり、人々の生活が根底から変わりはじめた - 分裂勘違い君劇場 by ふろむだ https://www.furomuda.com/entry/20080302/1204438491]",
      "userId": "582e63d27c56960011aff09e",
      "created": 1538548791,
      "updated": 1538548804
    },
    {
      "id": "5bb46444aff09e000019d825",
      "text": "  [とくに好きな仕事でなくても、すばらしい幸福感に包まれて仕事をする方法 - 分裂勘違い君劇場 by ふろむだ https://www.furomuda.com/entry/20080302/1204438490]",
      "userId": "582e63d27c56960011aff09e",
      "created": 1538548805,
      "updated": 1538548818
    },
    {
      "id": "5bb463ceaff09e000019d821",
      "text": "\t2008-04-09 [不運と理不尽に襲われたとき、うまく切り抜ける人と、逃げ切れずに酷い目に会う人の違い - 分裂勘違い君劇場 by ふろむだ https://www.furomuda.com/entry/20080409/1207702690]",
      "userId": "582e63d27c56960011aff09e",
      "created": 1538548686,
      "updated": 1538548686
    },
    {
      "id": "5bb463cfaff09e000019d822",
      "text": "",
      "userId": "582e63d27c56960011aff09e",
      "created": 1538548688,
      "updated": 1538548688
    },
    {
      "id": "5bb46377aff09e000019d81e",
      "text": "\t[404 Blog Not Found:小市民の敵は、小市民 http://blog.livedoor.jp/dankogai/archives/51010743.html]",
      "userId": "582e63d27c56960011aff09e",
      "created": 1538548599,
      "updated": 1538548600
    },
    {
      "id": "5bb462a1aff09e000019d814",
      "text": " [「マッチョしか選択肢がなかった人」 | おごちゃんの雑文 http://www.nurs.or.jp/~ogochan/essay/archives/1108]",
      "userId": "582e63d27c56960011aff09e",
      "created": 1538548386,
      "updated": 1538548387
    },
    {
      "id": "5bb46247aff09e000019d812",
      "text": "\t[20秒でわかる典型的なマッチョ・ウィンプ問答 - conflict error http://webkit.seesaa.net/article/129745879.html]",
      "userId": "582e63d27c56960011aff09e",
      "created": 1538548296,
      "updated": 1538548388
    },
    {
      "id": "5bb462b6aff09e000019d816",
      "text": " [弱虫が万年弱者である理由 | おごちゃんの雑文 http://www.nurs.or.jp/~ogochan/essay/archives/1171]",
      "userId": "582e63d27c56960011aff09e",
      "created": 1538548406,
      "updated": 1538548430
    },
    {
      "id": "5bb46319aff09e000019d817",
      "text": "",
      "userId": "582e63d27c56960011aff09e",
      "created": 1538548506,
      "updated": 1538548506
    },
    {
      "id": "5bb462b5aff09e000019d815",
      "text": "2014",
      "userId": "582e63d27c56960011aff09e",
      "created": 1538548406,
      "updated": 1538548508
    },
    {
      "id": "5bb4631baff09e000019d819",
      "text": "\t[Latest topics > アドラー心理学とマッチョ - outsider reflex https://piro.sakura.ne.jp/latest/blosxom.cgi/topics/2014-07-10_macho.htm]",
      "userId": "582e63d27c56960011aff09e",
      "created": 1538548508,
      "updated": 1538548508
    },
    {
      "id": "5bb4632eaff09e000019d81a",
      "text": " [アドラー心理学についての私の概観 - この夜が明けるまであと百万の祈り http://tyoshiki.hatenadiary.com/entry/2014/07/08/180324]",
      "userId": "582e63d27c56960011aff09e",
      "created": 1538548526,
      "updated": 1538548527
    },
    {
      "id": "5bb4631baff09e000019d818",
      "text": "",
      "userId": "582e63d27c56960011aff09e",
      "created": 1538548508,
      "updated": 1538548508
    }
  ]
}