{
  "id": "5c884db868ccf4001722052a",
  "title": "専門家はすべての失敗を経験した人",
  "created": 1552436669,
  "updated": 1552439167,
  "lines": [
    {
      "id": "5c884db868ccf4001722052a",
      "text": "専門家はすべての失敗を経験した人",
      "userId": "582e63d27c56960011aff09e",
      "created": 1552436669,
      "updated": 1552438569
    },
    {
      "id": "5c884dbcaff09e00007bee6b",
      "text": ">[専門家]とはすべての[失敗]を経験した人のことである。ある狭い領域で起こりうるすべての失敗を。",
      "userId": "582e63d27c56960011aff09e",
      "created": 1552436669,
      "updated": 1552439167
    },
    {
      "id": "5c884dcbaff09e00007bee6d",
      "text": "\t[Niels Bohr - Wikiquote https://en.wikiquote.org/wiki/Niels_Bohr]",
      "userId": "582e63d27c56960011aff09e",
      "created": 1552436683,
      "updated": 1552436803
    },
    {
      "id": "5c884e2faff09e00007bee6e",
      "text": "\t\tAn expert is a man who has made all the mistakes which can be made in a very narrow field.",
      "userId": "582e63d27c56960011aff09e",
      "created": 1552436783,
      "updated": 1552436808
    },
    {
      "id": "5c884e2faff09e00007bee6f",
      "text": "\t\tAs quoted by Edward Teller (10 October 1972), and A Dictionary of Scientific Quotations (1991) by Alan L. Mackay, p. 35",
      "userId": "582e63d27c56960011aff09e",
      "created": 1552436783,
      "updated": 1552436819
    },
    {
      "id": "5c884ec7aff09e00007bee71",
      "text": "",
      "userId": "582e63d27c56960011aff09e",
      "created": 1552436935,
      "updated": 1552436935
    },
    {
      "id": "5c884eccaff09e00007bee74",
      "text": "原文ではmistakeの修飾は後ろからなんだけども、日本語の係り受けだと前からになりがち",
      "userId": "582e63d27c56960011aff09e",
      "created": 1552436941,
      "updated": 1552438748
    },
    {
      "id": "5c884ec7aff09e00007bee72",
      "text": "\t参考訳: 専門家とは、非常に狭い分野で、ありとあらゆる失敗を重ねてきた人間のことである。",
      "userId": "582e63d27c56960011aff09e",
      "created": 1552436935,
      "updated": 1552438757
    },
    {
      "id": "5c884ec7aff09e00007bee73",
      "text": "\t重要なのは「すべての失敗」というところ",
      "userId": "582e63d27c56960011aff09e",
      "created": 1552436936,
      "updated": 1552438950
    },
    {
      "id": "5c8856a5aff09e00007bee7b",
      "text": "\t\tなのだが「非常に狭い分野で」という大きいフレーズと並んでしまうと「すべての」が目立たなくなってしまう",
      "userId": "582e63d27c56960011aff09e",
      "created": 1552438950,
      "updated": 1552438950
    },
    {
      "id": "5c885603aff09e00007bee78",
      "text": "\t「ありとあらゆる」と大きくすることで目立たせようとする意図は理解できる。",
      "userId": "582e63d27c56960011aff09e",
      "created": 1552438788,
      "updated": 1552438947
    },
    {
      "id": "5c8856a3aff09e00007bee7a",
      "text": "\t\tしかしこれはインパクトが強くなったと感じる人も弱くなったと感じる人もいそう",
      "userId": "582e63d27c56960011aff09e",
      "created": 1552438947,
      "updated": 1552439023
    },
    {
      "id": "5c8856f3aff09e00007bee7c",
      "text": "\t\t口頭だったらイントネーションで強調できるのだけど。",
      "userId": "582e63d27c56960011aff09e",
      "created": 1552439028,
      "updated": 1552439054
    },
    {
      "id": "5c88570daff09e00007bee7d",
      "text": "\tというわけで今回の僕の訳では2つに分割することにした",
      "userId": "582e63d27c56960011aff09e",
      "created": 1552439054,
      "updated": 1552439101
    },
    {
      "id": "5c884f86aff09e00007bee75",
      "text": "\t\t>専門家とはすべての失敗を経験した人のことである。",
      "userId": "582e63d27c56960011aff09e",
      "created": 1552437127,
      "updated": 1552439112
    },
    {
      "id": "5c885746aff09e00007bee80",
      "text": "\t\t>ある狭い領域で起こりうるすべての失敗を。",
      "userId": "582e63d27c56960011aff09e",
      "created": 1552439110,
      "updated": 1552439113
    },
    {
      "id": "5c885744aff09e00007bee7f",
      "text": "",
      "userId": "582e63d27c56960011aff09e",
      "created": 1552439108,
      "updated": 1552439108
    }
  ]
}