{
  "id": "5d199553487bbb001733b910",
  "title": "グループを作りたい時、そのグループの表札が既に存在する",
  "created": 1561957717,
  "updated": 1561957717,
  "lines": [
    {
      "id": "5d199553487bbb001733b910",
      "text": "グループを作りたい時、そのグループの表札が既に存在する",
      "userId": "582e63d27c56960011aff09e",
      "created": 1561957717,
      "updated": 1561957717
    },
    {
      "id": "5d199554aff09e0000b2b1c9",
      "text": "from [pRegroup2020]",
      "userId": "582e63d27c56960011aff09e",
      "created": 1561957717,
      "updated": 1609757744
    },
    {
      "id": "5d199554aff09e0000b2b1ca",
      "text": "グループを作りたい時、そのグループの表札が既に存在する",
      "userId": "582e63d27c56960011aff09e",
      "created": 1561957717,
      "updated": 1561957717
    },
    {
      "id": "5d199554aff09e0000b2b1cb",
      "text": "\tというシチュエーションはよくある",
      "userId": "582e63d27c56960011aff09e",
      "created": 1561957717,
      "updated": 1561957717
    },
    {
      "id": "5d199554aff09e0000b2b1cc",
      "text": "\t[https://gyazo.com/f0d7cebd4b23635d1d39016e2faac0e0]",
      "userId": "582e63d27c56960011aff09e",
      "created": 1561957717,
      "updated": 1561957717
    },
    {
      "id": "5d199554aff09e0000b2b1cd",
      "text": "\t投げ縄選択→グループ化→プレースホルダーの「表札付箋」が作られる",
      "userId": "582e63d27c56960011aff09e",
      "created": 1561957717,
      "updated": 1561957717
    },
    {
      "id": "5d199554aff09e0000b2b1ce",
      "text": "\t\tこの状態でグループ内の子付箋を",
      "userId": "582e63d27c56960011aff09e",
      "created": 1561957717,
      "updated": 1561957717
    },
    {
      "id": "5d199554aff09e0000b2b1cf",
      "text": "\t\t\tクリック",
      "userId": "582e63d27c56960011aff09e",
      "created": 1561957717,
      "updated": 1561957717
    },
    {
      "id": "5d199554aff09e0000b2b1d0",
      "text": "\t\t\tドラッグして表札にドロップ",
      "userId": "582e63d27c56960011aff09e",
      "created": 1561957717,
      "updated": 1561957717
    },
    {
      "id": "5d199554aff09e0000b2b1d1",
      "text": "\t\tで表札にできれば良い",
      "userId": "582e63d27c56960011aff09e",
      "created": 1561957717,
      "updated": 1561957717
    },
    {
      "id": "5d199554aff09e0000b2b1d2",
      "text": "\t\t僕はクリックで良いと思うがドラッグドロップの方が自然か？？",
      "userId": "582e63d27c56960011aff09e",
      "created": 1561957717,
      "updated": 1561957717
    },
    {
      "id": "5d199554aff09e0000b2b1d3",
      "text": "\tこの機能がないと",
      "userId": "582e63d27c56960011aff09e",
      "created": 1561957717,
      "updated": 1561957717
    },
    {
      "id": "5d199554aff09e0000b2b1d4",
      "text": "\t\tXをのぞいてグループ化",
      "userId": "582e63d27c56960011aff09e",
      "created": 1561957717,
      "updated": 1561957717
    },
    {
      "id": "5d199554aff09e0000b2b1d5",
      "text": "\t\tXと同じ内容の表札を作る",
      "userId": "582e63d27c56960011aff09e",
      "created": 1561957717,
      "updated": 1561957717
    },
    {
      "id": "5d199554aff09e0000b2b1d6",
      "text": "\t\tXを削除",
      "userId": "582e63d27c56960011aff09e",
      "created": 1561957717,
      "updated": 1561957717
    },
    {
      "id": "5d199554aff09e0000b2b1d7",
      "text": "\tという手間になる",
      "userId": "582e63d27c56960011aff09e",
      "created": 1561957717,
      "updated": 1561957717
    },
    {
      "id": "5d199554aff09e0000b2b1d8",
      "text": "",
      "userId": "582e63d27c56960011aff09e",
      "created": 1561957717,
      "updated": 1561957717
    }
  ]
}