{
  "id": "5f0e5e0364ae1700387f5a97",
  "title": "最小費用流の双対",
  "created": 1594777096,
  "updated": 1594777129,
  "lines": [
    {
      "id": "5f0e5e0364ae1700387f5a97",
      "text": "最小費用流の双対",
      "userId": "582e63d27c56960011aff09e",
      "created": 1594777096,
      "updated": 1594777098
    },
    {
      "id": "5f0e5e0aaff09e000041d5f2",
      "text": "https://beet-aizu.hatenablog.com/entry/2019/10/20/150649",
      "userId": "582e63d27c56960011aff09e",
      "created": 1594777098,
      "updated": 1594777099
    },
    {
      "id": "5f0e5e0baff09e000041d5f3",
      "text": "[最小費用流]の[LP双対]",
      "userId": "582e63d27c56960011aff09e",
      "created": 1594777099,
      "updated": 1594777129
    },
    {
      "id": "5f0e5e0faff09e000041d5f4",
      "text": "",
      "userId": "582e63d27c56960011aff09e",
      "created": 1594777103,
      "updated": 1594777103
    }
  ]
}