{
  "id": "619d3786d615c20022254641",
  "title": "ジェルコートF",
  "created": 1637693323,
  "updated": 1637693390,
  "lines": [
    {
      "id": "619d3786d615c20022254641",
      "text": "ジェルコートF",
      "userId": "582e63d27c56960011aff09e",
      "created": 1637693323,
      "updated": 1637693325
    },
    {
      "id": "619d378caff09e000037153c",
      "text": "https://www.weltecnet.co.jp/products/concool/gelcoatf/",
      "userId": "582e63d27c56960011aff09e",
      "created": 1637693325,
      "updated": 1637693342
    },
    {
      "id": "619d379aaff09e000037153e",
      "text": "",
      "userId": "582e63d27c56960011aff09e",
      "created": 1637693358,
      "updated": 1637693358
    },
    {
      "id": "619d37aeaff09e0000371540",
      "text": "[フッ化ナトリウム]950ppmF（薬用成分）、[塩酸クロルヘキシジン]（薬用成分）、[β―グリチルレチン酸]（薬用成分）、[ポリリン酸ナトリウム]（キレート剤）、[キシリトール]（甘味料）",
      "userId": "582e63d27c56960011aff09e",
      "created": 1637693358,
      "updated": 1637693388
    },
    {
      "id": "619d37cdaff09e0000371541",
      "text": "",
      "userId": "582e63d27c56960011aff09e",
      "created": 1637693390,
      "updated": 1637693390
    },
    {
      "id": "619d37a9aff09e000037153f",
      "text": "[オーラルケア]",
      "userId": "582e63d27c56960011aff09e",
      "created": 1637693358,
      "updated": 1637693358
    },
    {
      "id": "619d379aaff09e000037153d",
      "text": "",
      "userId": "582e63d27c56960011aff09e",
      "created": 1637693342,
      "updated": 1637693342
    }
  ]
}