{
  "id": "61ec2c6668e992001d9ec10f",
  "title": "日本語プロジェクトと英語プロジェクトを一つのプロジェクトに",
  "created": 1642867814,
  "updated": 1642868141,
  "lines": [
    {
      "id": "61ec2c6668e992001d9ec10f",
      "text": "日本語プロジェクトと英語プロジェクトを一つのプロジェクトに",
      "userId": "582e63d27c56960011aff09e",
      "created": 1642867814,
      "updated": 1642867814
    },
    {
      "id": "61ec2c66aff09e00007ffcbf",
      "text": "from [井戸端2022-01-20]",
      "userId": "582e63d27c56960011aff09e",
      "created": 1642867814,
      "updated": 1642867814
    },
    {
      "id": "61ec2c66aff09e00007ffcc0",
      "text": "日本語プロジェクトと英語プロジェクトを一つのプロジェクトに",
      "userId": "582e63d27c56960011aff09e",
      "created": 1642867814,
      "updated": 1642867814
    },
    {
      "id": "61ec2c66aff09e00007ffcc1",
      "text": "　[複数言語でScrapboxを運用する]",
      "userId": "582e63d27c56960011aff09e",
      "created": 1642867814,
      "updated": 1642868056
    },
    {
      "id": "61ec2ceaaff09e000037e6a1",
      "text": "　[/villagepump/複数のprojectを透過的に扱う]",
      "userId": "582e63d27c56960011aff09e",
      "created": 1642867946,
      "updated": 1642868056
    },
    {
      "id": "61ec2c66aff09e00007ffcc2",
      "text": "　自分の日本語プロジェクトと英語プロジェクトをどうやって透過的に扱おうかなと頭を悩ませてたけど、そもそも一つのプロジェクトにしたらいいのかもと思い始めた",
      "userId": "582e63d27c56960011aff09e",
      "created": 1642867814,
      "updated": 1642868056
    },
    {
      "id": "61ec2c66aff09e00007ffcc3",
      "text": "　　なぜプロジェクトを分けたのか",
      "userId": "582e63d27c56960011aff09e",
      "created": 1642867814,
      "updated": 1642868065
    },
    {
      "id": "61ec2d60aff09e000037e6a3",
      "text": "　　\t英語しか読めない人にとって僕の日本語プロジェクトのトップページはゴミの山に見えるから",
      "userId": "582e63d27c56960011aff09e",
      "created": 1642868065,
      "updated": 1642868065
    },
    {
      "id": "61ec2c66aff09e00007ffcc4",
      "text": "　　その結果、相互に関係のあるプロジェクトが分断された",
      "userId": "582e63d27c56960011aff09e",
      "created": 1642867814,
      "updated": 1642868072
    },
    {
      "id": "61ec2d67aff09e000037e6a4",
      "text": "　　\t「プロジェクト間のつながりを発見する仕組みが必要」と思うようになった",
      "userId": "582e63d27c56960011aff09e",
      "created": 1642868072,
      "updated": 1642868072
    },
    {
      "id": "61ec2d5caff09e000037e6a2",
      "text": "",
      "userId": "582e63d27c56960011aff09e",
      "created": 1642868061,
      "updated": 1642868061
    },
    {
      "id": "61ec2c66aff09e00007ffcc5",
      "text": "　　本質的に必要だったのは「英語話者向けコンテンツだけ絞り込んだビュー」だったのでは",
      "userId": "582e63d27c56960011aff09e",
      "created": 1642867814,
      "updated": 1642868077
    },
    {
      "id": "61ec2c66aff09e00007ffcc6",
      "text": "　　　Scrapboxは絞り込んだものに対してのビューがえらべないからそれを実現できなかった",
      "userId": "582e63d27c56960011aff09e",
      "created": 1642867814,
      "updated": 1642868107
    },
    {
      "id": "61ec2c66aff09e00007ffcc7",
      "text": "　　　[Scrapbox Reader]でできるかも？",
      "userId": "582e63d27c56960011aff09e",
      "created": 1642867814,
      "updated": 1642868130
    },
    {
      "id": "61ec2c66aff09e00007ffcc9",
      "text": "　　　 [アイコン記法で属性表現]して英語話者向けフラグを立てれば",
      "userId": "582e63d27c56960011aff09e",
      "created": 1642867814,
      "updated": 1642868123
    },
    {
      "id": "61ec2c66aff09e00007ffcca",
      "text": "　　　　全部のページに特定のアイコン記法を書いて…めんどくさいな…",
      "userId": "582e63d27c56960011aff09e",
      "created": 1642867814,
      "updated": 1642868123
    },
    {
      "id": "61ec2c66aff09e00007ffccb",
      "text": "　　　　自動書き込みすればそこまで面倒でもなさそう[/villagepump/takker.icon]",
      "userId": "582e63d27c56960011aff09e",
      "created": 1642867814,
      "updated": 1642868123
    },
    {
      "id": "61ec2c66aff09e00007ffccc",
      "text": "　開発しつつあるものの根本的存在理由に関わる疑念が発生してしまったとき、どうすればいいのかw",
      "userId": "582e63d27c56960011aff09e",
      "created": 1642867814,
      "updated": 1642868135
    },
    {
      "id": "61ec2c66aff09e00007ffccd",
      "text": "\t方針定まった",
      "userId": "582e63d27c56960011aff09e",
      "created": 1642867814,
      "updated": 1642868141
    },
    {
      "id": "61ec2c66aff09e00007ffcce",
      "text": "\t [ScrapboxAutoTransプロジェクトの今後の進め方について方針が決まると良い]",
      "userId": "582e63d27c56960011aff09e",
      "created": 1642867814,
      "updated": 1642868141
    },
    {
      "id": "61ec2c66aff09e00007ffccf",
      "text": "\t\t機械翻訳は一旦ペンディング",
      "userId": "582e63d27c56960011aff09e",
      "created": 1642867814,
      "updated": 1642868141
    },
    {
      "id": "61ec2c66aff09e00007ffcd0",
      "text": "  二つのプロジェクトをScrapbox上でマージする",
      "userId": "582e63d27c56960011aff09e",
      "created": 1642867814,
      "updated": 1642868141
    },
    {
      "id": "61ec2c66aff09e00007ffcd1",
      "text": "  　英語版のプロジェクトにアイコン記法で英語である旨のフラグを立てる",
      "userId": "582e63d27c56960011aff09e",
      "created": 1642867814,
      "updated": 1642868141
    },
    {
      "id": "61ec2c66aff09e00007ffcd2",
      "text": "  ScrapboxReaderで英語話者向けに英語フラグ付きのものだけを表示するビューを作る",
      "userId": "582e63d27c56960011aff09e",
      "created": 1642867814,
      "updated": 1642868141
    },
    {
      "id": "61ec2c66aff09e00007ffcd3",
      "text": "　マージした",
      "userId": "582e63d27c56960011aff09e",
      "created": 1642867814,
      "updated": 1642868141
    },
    {
      "id": "61ec2c66aff09e00007ffcd4",
      "text": "　特定のアイコンがついてる記事だけからランダム表示できるといいのにな",
      "userId": "582e63d27c56960011aff09e",
      "created": 1642867814,
      "updated": 1642867824
    },
    {
      "id": "61ec2c66aff09e00007ffcd5",
      "text": "　　プロジェクトをマージしたことの弊害の一つ",
      "userId": "582e63d27c56960011aff09e",
      "created": 1642867814,
      "updated": 1642867824
    }
  ]
}